tree_sitter_swift/__init__.py
tree_sitter_swift/__init__.pyi
tree_sitter_swift/_binding.abi3.so
tree_sitter_swift/binding.c
tree_sitter_swift/py.typed
tree_sitter_swift/queries/folds.scm
tree_sitter_swift/queries/highlights.scm
tree_sitter_swift/queries/indents.scm
tree_sitter_swift/queries/injections.scm
tree_sitter_swift/queries/locals.scm
tree_sitter_swift/queries/outline.scm
tree_sitter_swift/queries/tags.scm
tree_sitter_swift/queries/textobjects.scm
tree_sitter_swift-0.0.1.dist-info/METADATA
tree_sitter_swift-0.0.1.dist-info/WHEEL
tree_sitter_swift-0.0.1.dist-info/top_level.txt
tree_sitter_swift-0.0.1.dist-info/RECORD
tree_sitter_swift-0.0.1.dist-info/licenses/LICENSE
